{
  "generatedAt": "2026-07-02T21:43:56.862Z",
  "baseUrl": "http://localhost:3000",
  "expectedSeekSeconds": 14,
  "preSeekPosition": 1.673,
  "firstAnomaly": {
    "tMs": 7170,
    "field": "sliderValue",
    "value": 1,
    "expected": 14,
    "reason": "seek slider snap-back"
  },
  "anomalyCount": 138,
  "consoleLogs": [
    {
      "tMs": 1979,
      "text": "[SESSION] play() {refId: sara-landry::legacy, type: track}"
    },
    {
      "tMs": 1980,
      "text": "[ENGINE] play requested {refId: sara-landry::legacy, type: track, generation: 1, engineMounted: true}"
    },
    {
      "tMs": 1984,
      "text": "[PROVIDER] [PROVIDER SWITCH] {from: null, to: spotify, refId: sara-landry::legacy}"
    },
    {
      "tMs": 1984,
      "text": "[PROVIDER] [PROVIDER INIT] {kind: spotify}"
    },
    {
      "tMs": 1984,
      "text": "[PROVIDER] [PROVIDER LOAD] {kind: spotify, refId: sara-landry::legacy, sourceUrl: https://open.spotify.com/track/0aMonkh8OKgqx1K0viRHRT, generation: 1}"
    },
    {
      "tMs": 1984,
      "text": "[PROVIDER] [PROVIDER LOAD] {kind: spotify, refId: sara-landry::legacy, uri: spotify:track:0aMonkh8OKgqx1K0viRHRT}"
    },
    {
      "tMs": 1984,
      "text": "[PROVIDER] [PROVIDER STATE] {kind: spotify, isPlaying: false, isLoading: true, currentTime: 0, duration: 0}"
    },
    {
      "tMs": 3917,
      "text": "[PROVIDER] [PROVIDER STATE] {kind: spotify, isPlaying: false, isLoading: false, currentTime: 0, duration: 0}"
    },
    {
      "tMs": 3932,
      "text": "[PROVIDER] [PROVIDER PLAY] {kind: spotify, refId: sara-landry::legacy}"
    },
    {
      "tMs": 4141,
      "text": "[PROVIDER] [PROVIDER STATE] {kind: spotify, isPlaying: true, isLoading: true, currentTime: 0, duration: 0}"
    },
    {
      "tMs": 4884,
      "text": "[PROVIDER] [PROVIDER STATE] {kind: spotify, isPlaying: true, isLoading: true, currentTime: 0, duration: 29.713}"
    },
    {
      "tMs": 4888,
      "text": "[PROVIDER] [PROVIDER STATE] {kind: spotify, isPlaying: true, isLoading: false, currentTime: 0, duration: 29.713}"
    },
    {
      "tMs": 5772,
      "text": "[PROVIDER] [PROVIDER STATE] {kind: spotify, isPlaying: true, isLoading: false, currentTime: 0, duration: 29.713}"
    },
    {
      "tMs": 5901,
      "text": "[PROVIDER] [PROVIDER STATE] {kind: spotify, isPlaying: true, isLoading: false, currentTime: 0.622, duration: 29.713}"
    },
    {
      "tMs": 6964,
      "text": "[PROVIDER] [PROVIDER STATE] {kind: spotify, isPlaying: true, isLoading: false, currentTime: 1.673, duration: 29.713}"
    },
    {
      "tMs": 8026,
      "text": "[PROVIDER] [PROVIDER STATE] {kind: spotify, isPlaying: true, isLoading: false, currentTime: 2.737, duration: 29.713}"
    },
    {
      "tMs": 9089,
      "text": "[PROVIDER] [PROVIDER STATE] {kind: spotify, isPlaying: true, isLoading: false, currentTime: 3.802, duration: 29.713}"
    }
  ],
  "timeline": [
    {
      "tMs": 1918,
      "phase": "pre-play",
      "controllerCurrentTime": 0,
      "controllerPendingSeek": null,
      "controllerIsSeeking": false,
      "controllerSeekPreview": null,
      "engineCurrentTime": 0,
      "engineDuration": 0,
      "storeCurrentTime": 0,
      "storeDuration": 0,
      "audioCurrentTime": null,
      "sliderValue": null,
      "sliderMax": null,
      "elapsedLabel": null,
      "displayTimeFromSnapshot": 0
    },
    {
      "tMs": 7054,
      "phase": "post-play-5s",
      "controllerCurrentTime": 1.673,
      "controllerPendingSeek": null,
      "controllerIsSeeking": false,
      "controllerSeekPreview": null,
      "engineCurrentTime": 1.673,
      "engineDuration": 29.713,
      "storeCurrentTime": 1.673,
      "storeDuration": 29.713,
      "audioCurrentTime": null,
      "sliderValue": 1,
      "sliderMax": 29,
      "elapsedLabel": "0:01",
      "displayTimeFromSnapshot": 1.673
    },
    {
      "tMs": 7055,
      "phase": "pre-seek",
      "controllerCurrentTime": 1.673,
      "controllerPendingSeek": null,
      "controllerIsSeeking": false,
      "controllerSeekPreview": null,
      "engineCurrentTime": 1.673,
      "engineDuration": 29.713,
      "storeCurrentTime": 1.673,
      "storeDuration": 29.713,
      "audioCurrentTime": null,
      "sliderValue": 1,
      "sliderMax": 29,
      "elapsedLabel": "0:01",
      "displayTimeFromSnapshot": 1.673
    },
    {
      "tMs": 7075,
      "phase": "during-settle",
      "controllerCurrentTime": 1.673,
      "controllerPendingSeek": null,
      "controllerIsSeeking": false,
      "controllerSeekPreview": null,
      "engineCurrentTime": 1.673,
      "engineDuration": 29.713,
      "storeCurrentTime": 1.673,
      "storeDuration": 29.713,
      "audioCurrentTime": null,
      "sliderValue": 1,
      "sliderMax": 29,
      "elapsedLabel": "0:01",
      "displayTimeFromSnapshot": 1.673
    },
    {
      "tMs": 7115,
      "phase": "during-settle",
      "controllerCurrentTime": 1.673,
      "controllerPendingSeek": 15,
      "controllerIsSeeking": true,
      "controllerSeekPreview": 15,
      "engineCurrentTime": 1.673,
      "engineDuration": 29.713,
      "storeCurrentTime": 1.673,
      "storeDuration": 29.713,
      "audioCurrentTime": null,
      "sliderValue": 1,
      "sliderMax": 29,
      "elapsedLabel": "0:01",
      "displayTimeFromSnapshot": 15
    },
    {
      "tMs": 7117,
      "phase": "seek-pointerdown",
      "controllerCurrentTime": 1.673,
      "controllerPendingSeek": 15,
      "controllerIsSeeking": true,
      "controllerSeekPreview": 15,
      "engineCurrentTime": 1.673,
      "engineDuration": 29.713,
      "storeCurrentTime": 1.673,
      "storeDuration": 29.713,
      "audioCurrentTime": null,
      "sliderValue": 1,
      "sliderMax": 29,
      "elapsedLabel": "0:01",
      "displayTimeFromSnapshot": 15,
      "note": "pointerdown at 50%"
    },
    {
      "tMs": 7136,
      "phase": "during-settle",
      "controllerCurrentTime": 1.673,
      "controllerPendingSeek": 15,
      "controllerIsSeeking": true,
      "controllerSeekPreview": 15,
      "engineCurrentTime": 1.673,
      "engineDuration": 29.713,
      "storeCurrentTime": 1.673,
      "storeDuration": 29.713,
      "audioCurrentTime": null,
      "sliderValue": 1,
      "sliderMax": 29,
      "elapsedLabel": "0:01",
      "displayTimeFromSnapshot": 15
    },
    {
      "tMs": 7154,
      "phase": "during-settle",
      "controllerCurrentTime": 1.673,
      "controllerPendingSeek": 15,
      "controllerIsSeeking": true,
      "controllerSeekPreview": 15,
      "engineCurrentTime": 1.673,
      "engineDuration": 29.713,
      "storeCurrentTime": 1.673,
      "storeDuration": 29.713,
      "audioCurrentTime": null,
      "sliderValue": 1,
      "sliderMax": 29,
      "elapsedLabel": "0:01",
      "displayTimeFromSnapshot": 15
    },
    {
      "tMs": 7170,
      "phase": "seek-pointerup+0ms",
      "controllerCurrentTime": 1.673,
      "controllerPendingSeek": 15,
      "controllerIsSeeking": true,
      "controllerSeekPreview": 15,
      "engineCurrentTime": 1.673,
      "engineDuration": 29.713,
      "storeCurrentTime": 1.673,
      "storeDuration": 29.713,
      "audioCurrentTime": null,
      "sliderValue": 1,
      "sliderMax": 29,
      "elapsedLabel": "0:01",
      "displayTimeFromSnapshot": 15,
      "note": "pointerup commit"
    },
    {
      "tMs": 7171,
      "phase": "during-settle",
      "controllerCurrentTime": 1.673,
      "controllerPendingSeek": 15,
      "controllerIsSeeking": true,
      "controllerSeekPreview": 15,
      "engineCurrentTime": 1.673,
      "engineDuration": 29.713,
      "storeCurrentTime": 1.673,
      "storeDuration": 29.713,
      "audioCurrentTime": null,
      "sliderValue": 1,
      "sliderMax": 29,
      "elapsedLabel": "0:01",
      "displayTimeFromSnapshot": 15
    },
    {
      "tMs": 7190,
      "phase": "during-settle",
      "controllerCurrentTime": 1.673,
      "controllerPendingSeek": 15,
      "controllerIsSeeking": true,
      "controllerSeekPreview": 15,
      "engineCurrentTime": 1.673,
      "engineDuration": 29.713,
      "storeCurrentTime": 1.673,
      "storeDuration": 29.713,
      "audioCurrentTime": null,
      "sliderValue": 1,
      "sliderMax": 29,
      "elapsedLabel": "0:01",
      "displayTimeFromSnapshot": 15
    },
    {
      "tMs": 7208,
      "phase": "during-settle",
      "controllerCurrentTime": 1.673,
      "controllerPendingSeek": 15,
      "controllerIsSeeking": true,
      "controllerSeekPreview": 15,
      "engineCurrentTime": 1.673,
      "engineDuration": 29.713,
      "storeCurrentTime": 1.673,
      "storeDuration": 29.713,
      "audioCurrentTime": null,
      "sliderValue": 1,
      "sliderMax": 29,
      "elapsedLabel": "0:01",
      "displayTimeFromSnapshot": 15
    },
    {
      "tMs": 7226,
      "phase": "during-settle",
      "controllerCurrentTime": 1.673,
      "controllerPendingSeek": 15,
      "controllerIsSeeking": true,
      "controllerSeekPreview": 15,
      "engineCurrentTime": 1.673,
      "engineDuration": 29.713,
      "storeCurrentTime": 1.673,
      "storeDuration": 29.713,
      "audioCurrentTime": null,
      "sliderValue": 1,
      "sliderMax": 29,
      "elapsedLabel": "0:01",
      "displayTimeFromSnapshot": 15
    },
    {
      "tMs": 7245,
      "phase": "during-settle",
      "controllerCurrentTime": 1.673,
      "controllerPendingSeek": 15,
      "controllerIsSeeking": true,
      "controllerSeekPreview": 15,
      "engineCurrentTime": 1.673,
      "engineDuration": 29.713,
      "storeCurrentTime": 1.673,
      "storeDuration": 29.713,
      "audioCurrentTime": null,
      "sliderValue": 1,
      "sliderMax": 29,
      "elapsedLabel": "0:01",
      "displayTimeFromSnapshot": 15
    },
    {
      "tMs": 7263,
      "phase": "during-settle",
      "controllerCurrentTime": 1.673,
      "controllerPendingSeek": 15,
      "controllerIsSeeking": true,
      "controllerSeekPreview": 15,
      "engineCurrentTime": 1.673,
      "engineDuration": 29.713,
      "storeCurrentTime": 1.673,
      "storeDuration": 29.713,
      "audioCurrentTime": null,
      "sliderValue": 1,
      "sliderMax": 29,
      "elapsedLabel": "0:01",
      "displayTimeFromSnapshot": 15
    },
    {
      "tMs": 7282,
      "phase": "during-settle",
      "controllerCurrentTime": 1.673,
      "controllerPendingSeek": 15,
      "controllerIsSeeking": true,
      "controllerSeekPreview": 15,
      "engineCurrentTime": 1.673,
      "engineDuration": 29.713,
      "storeCurrentTime": 1.673,
      "storeDuration": 29.713,
      "audioCurrentTime": null,
      "sliderValue": 1,
      "sliderMax": 29,
      "elapsedLabel": "0:01",
      "displayTimeFromSnapshot": 15
    },
    {
      "tMs": 7300,
      "phase": "during-settle",
      "controllerCurrentTime": 1.673,
      "controllerPendingSeek": 15,
      "controllerIsSeeking": true,
      "controllerSeekPreview": 15,
      "engineCurrentTime": 1.673,
      "engineDuration": 29.713,
      "storeCurrentTime": 1.673,
      "storeDuration": 29.713,
      "audioCurrentTime": null,
      "sliderValue": 1,
      "sliderMax": 29,
      "elapsedLabel": "0:01",
      "displayTimeFromSnapshot": 15
    },
    {
      "tMs": 7318,
      "phase": "during-settle",
      "controllerCurrentTime": 1.673,
      "controllerPendingSeek": 15,
      "controllerIsSeeking": true,
      "controllerSeekPreview": 15,
      "engineCurrentTime": 1.673,
      "engineDuration": 29.713,
      "storeCurrentTime": 1.673,
      "storeDuration": 29.713,
      "audioCurrentTime": null,
      "sliderValue": 1,
      "sliderMax": 29,
      "elapsedLabel": "0:01",
      "displayTimeFromSnapshot": 15
    },
    {
      "tMs": 7336,
      "phase": "during-settle",
      "controllerCurrentTime": 1.673,
      "controllerPendingSeek": 15,
      "controllerIsSeeking": true,
      "controllerSeekPreview": 15,
      "engineCurrentTime": 1.673,
      "engineDuration": 29.713,
      "storeCurrentTime": 1.673,
      "storeDuration": 29.713,
      "audioCurrentTime": null,
      "sliderValue": 1,
      "sliderMax": 29,
      "elapsedLabel": "0:01",
      "displayTimeFromSnapshot": 15
    },
    {
      "tMs": 7354,
      "phase": "during-settle",
      "controllerCurrentTime": 1.673,
      "controllerPendingSeek": 15,
      "controllerIsSeeking": true,
      "controllerSeekPreview": 15,
      "engineCurrentTime": 1.673,
      "engineDuration": 29.713,
      "storeCurrentTime": 1.673,
      "storeDuration": 29.713,
      "audioCurrentTime": null,
      "sliderValue": 1,
      "sliderMax": 29,
      "elapsedLabel": "0:01",
      "displayTimeFromSnapshot": 15
    },
    {
      "tMs": 7372,
      "phase": "during-settle",
      "controllerCurrentTime": 1.673,
      "controllerPendingSeek": 15,
      "controllerIsSeeking": true,
      "controllerSeekPreview": 15,
      "engineCurrentTime": 1.673,
      "engineDuration": 29.713,
      "storeCurrentTime": 1.673,
      "storeDuration": 29.713,
      "audioCurrentTime": null,
      "sliderValue": 1,
      "sliderMax": 29,
      "elapsedLabel": "0:01",
      "displayTimeFromSnapshot": 15
    },
    {
      "tMs": 7391,
      "phase": "during-settle",
      "controllerCurrentTime": 1.673,
      "controllerPendingSeek": 15,
      "controllerIsSeeking": true,
      "controllerSeekPreview": 15,
      "engineCurrentTime": 1.673,
      "engineDuration": 29.713,
      "storeCurrentTime": 1.673,
      "storeDuration": 29.713,
      "audioCurrentTime": null,
      "sliderValue": 1,
      "sliderMax": 29,
      "elapsedLabel": "0:01",
      "displayTimeFromSnapshot": 15
    },
    {
      "tMs": 7409,
      "phase": "during-settle",
      "controllerCurrentTime": 1.673,
      "controllerPendingSeek": 15,
      "controllerIsSeeking": true,
      "controllerSeekPreview": 15,
      "engineCurrentTime": 1.673,
      "engineDuration": 29.713,
      "storeCurrentTime": 1.673,
      "storeDuration": 29.713,
      "audioCurrentTime": null,
      "sliderValue": 1,
      "sliderMax": 29,
      "elapsedLabel": "0:01",
      "displayTimeFromSnapshot": 15
    },
    {
      "tMs": 7426,
      "phase": "during-settle",
      "controllerCurrentTime": 1.673,
      "controllerPendingSeek": 15,
      "controllerIsSeeking": true,
      "controllerSeekPreview": 15,
      "engineCurrentTime": 1.673,
      "engineDuration": 29.713,
      "storeCurrentTime": 1.673,
      "storeDuration": 29.713,
      "audioCurrentTime": null,
      "sliderValue": 1,
      "sliderMax": 29,
      "elapsedLabel": "0:01",
      "displayTimeFromSnapshot": 15
    },
    {
      "tMs": 7444,
      "phase": "during-settle",
      "controllerCurrentTime": 1.673,
      "controllerPendingSeek": 15,
      "controllerIsSeeking": true,
      "controllerSeekPreview": 15,
      "engineCurrentTime": 1.673,
      "engineDuration": 29.713,
      "storeCurrentTime": 1.673,
      "storeDuration": 29.713,
      "audioCurrentTime": null,
      "sliderValue": 1,
      "sliderMax": 29,
      "elapsedLabel": "0:01",
      "displayTimeFromSnapshot": 15
    },
    {
      "tMs": 7462,
      "phase": "during-settle",
      "controllerCurrentTime": 1.673,
      "controllerPendingSeek": 15,
      "controllerIsSeeking": true,
      "controllerSeekPreview": 15,
      "engineCurrentTime": 1.673,
      "engineDuration": 29.713,
      "storeCurrentTime": 1.673,
      "storeDuration": 29.713,
      "audioCurrentTime": null,
      "sliderValue": 1,
      "sliderMax": 29,
      "elapsedLabel": "0:01",
      "displayTimeFromSnapshot": 15
    },
    {
      "tMs": 7480,
      "phase": "during-settle",
      "controllerCurrentTime": 1.673,
      "controllerPendingSeek": 15,
      "controllerIsSeeking": true,
      "controllerSeekPreview": 15,
      "engineCurrentTime": 1.673,
      "engineDuration": 29.713,
      "storeCurrentTime": 1.673,
      "storeDuration": 29.713,
      "audioCurrentTime": null,
      "sliderValue": 1,
      "sliderMax": 29,
      "elapsedLabel": "0:01",
      "displayTimeFromSnapshot": 15
    },
    {
      "tMs": 7498,
      "phase": "during-settle",
      "controllerCurrentTime": 1.673,
      "controllerPendingSeek": 15,
      "controllerIsSeeking": true,
      "controllerSeekPreview": 15,
      "engineCurrentTime": 1.673,
      "engineDuration": 29.713,
      "storeCurrentTime": 1.673,
      "storeDuration": 29.713,
      "audioCurrentTime": null,
      "sliderValue": 1,
      "sliderMax": 29,
      "elapsedLabel": "0:01",
      "displayTimeFromSnapshot": 15
    },
    {
      "tMs": 7517,
      "phase": "during-settle",
      "controllerCurrentTime": 1.673,
      "controllerPendingSeek": 15,
      "controllerIsSeeking": true,
      "controllerSeekPreview": 15,
      "engineCurrentTime": 1.673,
      "engineDuration": 29.713,
      "storeCurrentTime": 1.673,
      "storeDuration": 29.713,
      "audioCurrentTime": null,
      "sliderValue": 1,
      "sliderMax": 29,
      "elapsedLabel": "0:01",
      "displayTimeFromSnapshot": 15
    },
    {
      "tMs": 7535,
      "phase": "during-settle",
      "controllerCurrentTime": 1.673,
      "controllerPendingSeek": 15,
      "controllerIsSeeking": true,
      "controllerSeekPreview": 15,
      "engineCurrentTime": 1.673,
      "engineDuration": 29.713,
      "storeCurrentTime": 1.673,
      "storeDuration": 29.713,
      "audioCurrentTime": null,
      "sliderValue": 1,
      "sliderMax": 29,
      "elapsedLabel": "0:01",
      "displayTimeFromSnapshot": 15
    },
    {
      "tMs": 7554,
      "phase": "during-settle",
      "controllerCurrentTime": 1.673,
      "controllerPendingSeek": 15,
      "controllerIsSeeking": true,
      "controllerSeekPreview": 15,
      "engineCurrentTime": 1.673,
      "engineDuration": 29.713,
      "storeCurrentTime": 1.673,
      "storeDuration": 29.713,
      "audioCurrentTime": null,
      "sliderValue": 1,
      "sliderMax": 29,
      "elapsedLabel": "0:01",
      "displayTimeFromSnapshot": 15
    },
    {
      "tMs": 7573,
      "phase": "during-settle",
      "controllerCurrentTime": 1.673,
      "controllerPendingSeek": 15,
      "controllerIsSeeking": true,
      "controllerSeekPreview": 15,
      "engineCurrentTime": 1.673,
      "engineDuration": 29.713,
      "storeCurrentTime": 1.673,
      "storeDuration": 29.713,
      "audioCurrentTime": null,
      "sliderValue": 1,
      "sliderMax": 29,
      "elapsedLabel": "0:01",
      "displayTimeFromSnapshot": 15
    },
    {
      "tMs": 7592,
      "phase": "during-settle",
      "controllerCurrentTime": 1.673,
      "controllerPendingSeek": 15,
      "controllerIsSeeking": true,
      "controllerSeekPreview": 15,
      "engineCurrentTime": 1.673,
      "engineDuration": 29.713,
      "storeCurrentTime": 1.673,
      "storeDuration": 29.713,
      "audioCurrentTime": null,
      "sliderValue": 1,
      "sliderMax": 29,
      "elapsedLabel": "0:01",
      "displayTimeFromSnapshot": 15
    },
    {
      "tMs": 7612,
      "phase": "during-settle",
      "controllerCurrentTime": 1.673,
      "controllerPendingSeek": 15,
      "controllerIsSeeking": true,
      "controllerSeekPreview": 15,
      "engineCurrentTime": 1.673,
      "engineDuration": 29.713,
      "storeCurrentTime": 1.673,
      "storeDuration": 29.713,
      "audioCurrentTime": null,
      "sliderValue": 1,
      "sliderMax": 29,
      "elapsedLabel": "0:01",
      "displayTimeFromSnapshot": 15
    },
    {
      "tMs": 7630,
      "phase": "during-settle",
      "controllerCurrentTime": 1.673,
      "controllerPendingSeek": 15,
      "controllerIsSeeking": true,
      "controllerSeekPreview": 15,
      "engineCurrentTime": 1.673,
      "engineDuration": 29.713,
      "storeCurrentTime": 1.673,
      "storeDuration": 29.713,
      "audioCurrentTime": null,
      "sliderValue": 1,
      "sliderMax": 29,
      "elapsedLabel": "0:01",
      "displayTimeFromSnapshot": 15
    },
    {
      "tMs": 7650,
      "phase": "during-settle",
      "controllerCurrentTime": 1.673,
      "controllerPendingSeek": 15,
      "controllerIsSeeking": true,
      "controllerSeekPreview": 15,
      "engineCurrentTime": 1.673,
      "engineDuration": 29.713,
      "storeCurrentTime": 1.673,
      "storeDuration": 29.713,
      "audioCurrentTime": null,
      "sliderValue": 1,
      "sliderMax": 29,
      "elapsedLabel": "0:01",
      "displayTimeFromSnapshot": 15
    },
    {
      "tMs": 7669,
      "phase": "during-settle",
      "controllerCurrentTime": 1.673,
      "controllerPendingSeek": 15,
      "controllerIsSeeking": true,
      "controllerSeekPreview": 15,
      "engineCurrentTime": 1.673,
      "engineDuration": 29.713,
      "storeCurrentTime": 1.673,
      "storeDuration": 29.713,
      "audioCurrentTime": null,
      "sliderValue": 1,
      "sliderMax": 29,
      "elapsedLabel": "0:01",
      "displayTimeFromSnapshot": 15
    },
    {
      "tMs": 7688,
      "phase": "during-settle",
      "controllerCurrentTime": 1.673,
      "controllerPendingSeek": 15,
      "controllerIsSeeking": true,
      "controllerSeekPreview": 15,
      "engineCurrentTime": 1.673,
      "engineDuration": 29.713,
      "storeCurrentTime": 1.673,
      "storeDuration": 29.713,
      "audioCurrentTime": null,
      "sliderValue": 1,
      "sliderMax": 29,
      "elapsedLabel": "0:01",
      "displayTimeFromSnapshot": 15
    },
    {
      "tMs": 7709,
      "phase": "during-settle",
      "controllerCurrentTime": 1.673,
      "controllerPendingSeek": 15,
      "controllerIsSeeking": true,
      "controllerSeekPreview": 15,
      "engineCurrentTime": 1.673,
      "engineDuration": 29.713,
      "storeCurrentTime": 1.673,
      "storeDuration": 29.713,
      "audioCurrentTime": null,
      "sliderValue": 1,
      "sliderMax": 29,
      "elapsedLabel": "0:01",
      "displayTimeFromSnapshot": 15
    },
    {
      "tMs": 7729,
      "phase": "during-settle",
      "controllerCurrentTime": 1.673,
      "controllerPendingSeek": 15,
      "controllerIsSeeking": true,
      "controllerSeekPreview": 15,
      "engineCurrentTime": 1.673,
      "engineDuration": 29.713,
      "storeCurrentTime": 1.673,
      "storeDuration": 29.713,
      "audioCurrentTime": null,
      "sliderValue": 1,
      "sliderMax": 29,
      "elapsedLabel": "0:01",
      "displayTimeFromSnapshot": 15
    },
    {
      "tMs": 7748,
      "phase": "during-settle",
      "controllerCurrentTime": 1.673,
      "controllerPendingSeek": 15,
      "controllerIsSeeking": true,
      "controllerSeekPreview": 15,
      "engineCurrentTime": 1.673,
      "engineDuration": 29.713,
      "storeCurrentTime": 1.673,
      "storeDuration": 29.713,
      "audioCurrentTime": null,
      "sliderValue": 1,
      "sliderMax": 29,
      "elapsedLabel": "0:01",
      "displayTimeFromSnapshot": 15
    },
    {
      "tMs": 7765,
      "phase": "during-settle",
      "controllerCurrentTime": 1.673,
      "controllerPendingSeek": 15,
      "controllerIsSeeking": true,
      "controllerSeekPreview": 15,
      "engineCurrentTime": 1.673,
      "engineDuration": 29.713,
      "storeCurrentTime": 1.673,
      "storeDuration": 29.713,
      "audioCurrentTime": null,
      "sliderValue": 1,
      "sliderMax": 29,
      "elapsedLabel": "0:01",
      "displayTimeFromSnapshot": 15
    },
    {
      "tMs": 7784,
      "phase": "during-settle",
      "controllerCurrentTime": 1.673,
      "controllerPendingSeek": 15,
      "controllerIsSeeking": true,
      "controllerSeekPreview": 15,
      "engineCurrentTime": 1.673,
      "engineDuration": 29.713,
      "storeCurrentTime": 1.673,
      "storeDuration": 29.713,
      "audioCurrentTime": null,
      "sliderValue": 1,
      "sliderMax": 29,
      "elapsedLabel": "0:01",
      "displayTimeFromSnapshot": 15
    },
    {
      "tMs": 7802,
      "phase": "during-settle",
      "controllerCurrentTime": 1.673,
      "controllerPendingSeek": 15,
      "controllerIsSeeking": true,
      "controllerSeekPreview": 15,
      "engineCurrentTime": 1.673,
      "engineDuration": 29.713,
      "storeCurrentTime": 1.673,
      "storeDuration": 29.713,
      "audioCurrentTime": null,
      "sliderValue": 1,
      "sliderMax": 29,
      "elapsedLabel": "0:01",
      "displayTimeFromSnapshot": 15
    },
    {
      "tMs": 7821,
      "phase": "during-settle",
      "controllerCurrentTime": 1.673,
      "controllerPendingSeek": 15,
      "controllerIsSeeking": true,
      "controllerSeekPreview": 15,
      "engineCurrentTime": 1.673,
      "engineDuration": 29.713,
      "storeCurrentTime": 1.673,
      "storeDuration": 29.713,
      "audioCurrentTime": null,
      "sliderValue": 1,
      "sliderMax": 29,
      "elapsedLabel": "0:01",
      "displayTimeFromSnapshot": 15
    },
    {
      "tMs": 7841,
      "phase": "during-settle",
      "controllerCurrentTime": 1.673,
      "controllerPendingSeek": 15,
      "controllerIsSeeking": true,
      "controllerSeekPreview": 15,
      "engineCurrentTime": 1.673,
      "engineDuration": 29.713,
      "storeCurrentTime": 1.673,
      "storeDuration": 29.713,
      "audioCurrentTime": null,
      "sliderValue": 1,
      "sliderMax": 29,
      "elapsedLabel": "0:01",
      "displayTimeFromSnapshot": 15
    },
    {
      "tMs": 7860,
      "phase": "during-settle",
      "controllerCurrentTime": 1.673,
      "controllerPendingSeek": 15,
      "controllerIsSeeking": true,
      "controllerSeekPreview": 15,
      "engineCurrentTime": 1.673,
      "engineDuration": 29.713,
      "storeCurrentTime": 1.673,
      "storeDuration": 29.713,
      "audioCurrentTime": null,
      "sliderValue": 1,
      "sliderMax": 29,
      "elapsedLabel": "0:01",
      "displayTimeFromSnapshot": 15
    },
    {
      "tMs": 7879,
      "phase": "during-settle",
      "controllerCurrentTime": 1.673,
      "controllerPendingSeek": 15,
      "controllerIsSeeking": true,
      "controllerSeekPreview": 15,
      "engineCurrentTime": 1.673,
      "engineDuration": 29.713,
      "storeCurrentTime": 1.673,
      "storeDuration": 29.713,
      "audioCurrentTime": null,
      "sliderValue": 1,
      "sliderMax": 29,
      "elapsedLabel": "0:01",
      "displayTimeFromSnapshot": 15
    },
    {
      "tMs": 7897,
      "phase": "during-settle",
      "controllerCurrentTime": 1.673,
      "controllerPendingSeek": 15,
      "controllerIsSeeking": true,
      "controllerSeekPreview": 15,
      "engineCurrentTime": 1.673,
      "engineDuration": 29.713,
      "storeCurrentTime": 1.673,
      "storeDuration": 29.713,
      "audioCurrentTime": null,
      "sliderValue": 1,
      "sliderMax": 29,
      "elapsedLabel": "0:01",
      "displayTimeFromSnapshot": 15
    },
    {
      "tMs": 7915,
      "phase": "during-settle",
      "controllerCurrentTime": 1.673,
      "controllerPendingSeek": 15,
      "controllerIsSeeking": true,
      "controllerSeekPreview": 15,
      "engineCurrentTime": 1.673,
      "engineDuration": 29.713,
      "storeCurrentTime": 1.673,
      "storeDuration": 29.713,
      "audioCurrentTime": null,
      "sliderValue": 1,
      "sliderMax": 29,
      "elapsedLabel": "0:01",
      "displayTimeFromSnapshot": 15
    },
    {
      "tMs": 7934,
      "phase": "during-settle",
      "controllerCurrentTime": 1.673,
      "controllerPendingSeek": 15,
      "controllerIsSeeking": true,
      "controllerSeekPreview": 15,
      "engineCurrentTime": 1.673,
      "engineDuration": 29.713,
      "storeCurrentTime": 1.673,
      "storeDuration": 29.713,
      "audioCurrentTime": null,
      "sliderValue": 1,
      "sliderMax": 29,
      "elapsedLabel": "0:01",
      "displayTimeFromSnapshot": 15
    },
    {
      "tMs": 7953,
      "phase": "during-settle",
      "controllerCurrentTime": 1.673,
      "controllerPendingSeek": 15,
      "controllerIsSeeking": true,
      "controllerSeekPreview": 15,
      "engineCurrentTime": 1.673,
      "engineDuration": 29.713,
      "storeCurrentTime": 1.673,
      "storeDuration": 29.713,
      "audioCurrentTime": null,
      "sliderValue": 1,
      "sliderMax": 29,
      "elapsedLabel": "0:01",
      "displayTimeFromSnapshot": 15
    },
    {
      "tMs": 7974,
      "phase": "during-settle",
      "controllerCurrentTime": 1.673,
      "controllerPendingSeek": 15,
      "controllerIsSeeking": true,
      "controllerSeekPreview": 15,
      "engineCurrentTime": 1.673,
      "engineDuration": 29.713,
      "storeCurrentTime": 1.673,
      "storeDuration": 29.713,
      "audioCurrentTime": null,
      "sliderValue": 1,
      "sliderMax": 29,
      "elapsedLabel": "0:01",
      "displayTimeFromSnapshot": 15
    },
    {
      "tMs": 7994,
      "phase": "during-settle",
      "controllerCurrentTime": 1.673,
      "controllerPendingSeek": 15,
      "controllerIsSeeking": true,
      "controllerSeekPreview": 15,
      "engineCurrentTime": 1.673,
      "engineDuration": 29.713,
      "storeCurrentTime": 1.673,
      "storeDuration": 29.713,
      "audioCurrentTime": null,
      "sliderValue": 1,
      "sliderMax": 29,
      "elapsedLabel": "0:01",
      "displayTimeFromSnapshot": 15
    },
    {
      "tMs": 8012,
      "phase": "during-settle",
      "controllerCurrentTime": 1.673,
      "controllerPendingSeek": 15,
      "controllerIsSeeking": true,
      "controllerSeekPreview": 15,
      "engineCurrentTime": 1.673,
      "engineDuration": 29.713,
      "storeCurrentTime": 1.673,
      "storeDuration": 29.713,
      "audioCurrentTime": null,
      "sliderValue": 1,
      "sliderMax": 29,
      "elapsedLabel": "0:01",
      "displayTimeFromSnapshot": 15
    },
    {
      "tMs": 8031,
      "phase": "during-settle",
      "controllerCurrentTime": 1.673,
      "controllerPendingSeek": 15,
      "controllerIsSeeking": true,
      "controllerSeekPreview": 15,
      "engineCurrentTime": 2.737,
      "engineDuration": 29.713,
      "storeCurrentTime": 1.673,
      "storeDuration": 29.713,
      "audioCurrentTime": null,
      "sliderValue": 1,
      "sliderMax": 29,
      "elapsedLabel": "0:01",
      "displayTimeFromSnapshot": 15
    },
    {
      "tMs": 8049,
      "phase": "during-settle",
      "controllerCurrentTime": 1.673,
      "controllerPendingSeek": 15,
      "controllerIsSeeking": true,
      "controllerSeekPreview": 15,
      "engineCurrentTime": 2.737,
      "engineDuration": 29.713,
      "storeCurrentTime": 1.673,
      "storeDuration": 29.713,
      "audioCurrentTime": null,
      "sliderValue": 1,
      "sliderMax": 29,
      "elapsedLabel": "0:01",
      "displayTimeFromSnapshot": 15
    },
    {
      "tMs": 8067,
      "phase": "during-settle",
      "controllerCurrentTime": 1.673,
      "controllerPendingSeek": 15,
      "controllerIsSeeking": true,
      "controllerSeekPreview": 15,
      "engineCurrentTime": 2.737,
      "engineDuration": 29.713,
      "storeCurrentTime": 1.673,
      "storeDuration": 29.713,
      "audioCurrentTime": null,
      "sliderValue": 1,
      "sliderMax": 29,
      "elapsedLabel": "0:01",
      "displayTimeFromSnapshot": 15
    },
    {
      "tMs": 8085,
      "phase": "during-settle",
      "controllerCurrentTime": 1.673,
      "controllerPendingSeek": 15,
      "controllerIsSeeking": true,
      "controllerSeekPreview": 15,
      "engineCurrentTime": 2.737,
      "engineDuration": 29.713,
      "storeCurrentTime": 1.673,
      "storeDuration": 29.713,
      "audioCurrentTime": null,
      "sliderValue": 1,
      "sliderMax": 29,
      "elapsedLabel": "0:01",
      "displayTimeFromSnapshot": 15
    },
    {
      "tMs": 8104,
      "phase": "during-settle",
      "controllerCurrentTime": 1.673,
      "controllerPendingSeek": 15,
      "controllerIsSeeking": true,
      "controllerSeekPreview": 15,
      "engineCurrentTime": 2.737,
      "engineDuration": 29.713,
      "storeCurrentTime": 1.673,
      "storeDuration": 29.713,
      "audioCurrentTime": null,
      "sliderValue": 1,
      "sliderMax": 29,
      "elapsedLabel": "0:01",
      "displayTimeFromSnapshot": 15
    },
    {
      "tMs": 8122,
      "phase": "during-settle",
      "controllerCurrentTime": 1.673,
      "controllerPendingSeek": 15,
      "controllerIsSeeking": true,
      "controllerSeekPreview": 15,
      "engineCurrentTime": 2.737,
      "engineDuration": 29.713,
      "storeCurrentTime": 1.673,
      "storeDuration": 29.713,
      "audioCurrentTime": null,
      "sliderValue": 1,
      "sliderMax": 29,
      "elapsedLabel": "0:01",
      "displayTimeFromSnapshot": 15
    },
    {
      "tMs": 8140,
      "phase": "during-settle",
      "controllerCurrentTime": 1.673,
      "controllerPendingSeek": 15,
      "controllerIsSeeking": true,
      "controllerSeekPreview": 15,
      "engineCurrentTime": 2.737,
      "engineDuration": 29.713,
      "storeCurrentTime": 1.673,
      "storeDuration": 29.713,
      "audioCurrentTime": null,
      "sliderValue": 1,
      "sliderMax": 29,
      "elapsedLabel": "0:01",
      "displayTimeFromSnapshot": 15
    },
    {
      "tMs": 8158,
      "phase": "during-settle",
      "controllerCurrentTime": 1.673,
      "controllerPendingSeek": 15,
      "controllerIsSeeking": true,
      "controllerSeekPreview": 15,
      "engineCurrentTime": 2.737,
      "engineDuration": 29.713,
      "storeCurrentTime": 1.673,
      "storeDuration": 29.713,
      "audioCurrentTime": null,
      "sliderValue": 1,
      "sliderMax": 29,
      "elapsedLabel": "0:01",
      "displayTimeFromSnapshot": 15
    },
    {
      "tMs": 8176,
      "phase": "during-settle",
      "controllerCurrentTime": 1.673,
      "controllerPendingSeek": 15,
      "controllerIsSeeking": true,
      "controllerSeekPreview": 15,
      "engineCurrentTime": 2.737,
      "engineDuration": 29.713,
      "storeCurrentTime": 1.673,
      "storeDuration": 29.713,
      "audioCurrentTime": null,
      "sliderValue": 1,
      "sliderMax": 29,
      "elapsedLabel": "0:01",
      "displayTimeFromSnapshot": 15
    },
    {
      "tMs": 8194,
      "phase": "during-settle",
      "controllerCurrentTime": 1.673,
      "controllerPendingSeek": 15,
      "controllerIsSeeking": true,
      "controllerSeekPreview": 15,
      "engineCurrentTime": 2.737,
      "engineDuration": 29.713,
      "storeCurrentTime": 1.673,
      "storeDuration": 29.713,
      "audioCurrentTime": null,
      "sliderValue": 1,
      "sliderMax": 29,
      "elapsedLabel": "0:01",
      "displayTimeFromSnapshot": 15
    },
    {
      "tMs": 8212,
      "phase": "during-settle",
      "controllerCurrentTime": 1.673,
      "controllerPendingSeek": 15,
      "controllerIsSeeking": true,
      "controllerSeekPreview": 15,
      "engineCurrentTime": 2.737,
      "engineDuration": 29.713,
      "storeCurrentTime": 1.673,
      "storeDuration": 29.713,
      "audioCurrentTime": null,
      "sliderValue": 1,
      "sliderMax": 29,
      "elapsedLabel": "0:01",
      "displayTimeFromSnapshot": 15
    },
    {
      "tMs": 8230,
      "phase": "during-settle",
      "controllerCurrentTime": 1.673,
      "controllerPendingSeek": 15,
      "controllerIsSeeking": true,
      "controllerSeekPreview": 15,
      "engineCurrentTime": 2.737,
      "engineDuration": 29.713,
      "storeCurrentTime": 1.673,
      "storeDuration": 29.713,
      "audioCurrentTime": null,
      "sliderValue": 1,
      "sliderMax": 29,
      "elapsedLabel": "0:01",
      "displayTimeFromSnapshot": 15
    },
    {
      "tMs": 8249,
      "phase": "during-settle",
      "controllerCurrentTime": 1.673,
      "controllerPendingSeek": 15,
      "controllerIsSeeking": true,
      "controllerSeekPreview": 15,
      "engineCurrentTime": 2.737,
      "engineDuration": 29.713,
      "storeCurrentTime": 1.673,
      "storeDuration": 29.713,
      "audioCurrentTime": null,
      "sliderValue": 1,
      "sliderMax": 29,
      "elapsedLabel": "0:01",
      "displayTimeFromSnapshot": 15
    },
    {
      "tMs": 8267,
      "phase": "during-settle",
      "controllerCurrentTime": 1.673,
      "controllerPendingSeek": 15,
      "controllerIsSeeking": true,
      "controllerSeekPreview": 15,
      "engineCurrentTime": 2.737,
      "engineDuration": 29.713,
      "storeCurrentTime": 1.673,
      "storeDuration": 29.713,
      "audioCurrentTime": null,
      "sliderValue": 1,
      "sliderMax": 29,
      "elapsedLabel": "0:01",
      "displayTimeFromSnapshot": 15
    },
    {
      "tMs": 8286,
      "phase": "during-settle",
      "controllerCurrentTime": 1.673,
      "controllerPendingSeek": 15,
      "controllerIsSeeking": true,
      "controllerSeekPreview": 15,
      "engineCurrentTime": 2.737,
      "engineDuration": 29.713,
      "storeCurrentTime": 1.673,
      "storeDuration": 29.713,
      "audioCurrentTime": null,
      "sliderValue": 1,
      "sliderMax": 29,
      "elapsedLabel": "0:01",
      "displayTimeFromSnapshot": 15
    },
    {
      "tMs": 8304,
      "phase": "during-settle",
      "controllerCurrentTime": 1.673,
      "controllerPendingSeek": 15,
      "controllerIsSeeking": true,
      "controllerSeekPreview": 15,
      "engineCurrentTime": 2.737,
      "engineDuration": 29.713,
      "storeCurrentTime": 1.673,
      "storeDuration": 29.713,
      "audioCurrentTime": null,
      "sliderValue": 1,
      "sliderMax": 29,
      "elapsedLabel": "0:01",
      "displayTimeFromSnapshot": 15
    },
    {
      "tMs": 8323,
      "phase": "during-settle",
      "controllerCurrentTime": 1.673,
      "controllerPendingSeek": 15,
      "controllerIsSeeking": true,
      "controllerSeekPreview": 15,
      "engineCurrentTime": 2.737,
      "engineDuration": 29.713,
      "storeCurrentTime": 1.673,
      "storeDuration": 29.713,
      "audioCurrentTime": null,
      "sliderValue": 1,
      "sliderMax": 29,
      "elapsedLabel": "0:01",
      "displayTimeFromSnapshot": 15
    },
    {
      "tMs": 8342,
      "phase": "during-settle",
      "controllerCurrentTime": 1.673,
      "controllerPendingSeek": 15,
      "controllerIsSeeking": true,
      "controllerSeekPreview": 15,
      "engineCurrentTime": 2.737,
      "engineDuration": 29.713,
      "storeCurrentTime": 1.673,
      "storeDuration": 29.713,
      "audioCurrentTime": null,
      "sliderValue": 1,
      "sliderMax": 29,
      "elapsedLabel": "0:01",
      "displayTimeFromSnapshot": 15
    },
    {
      "tMs": 8361,
      "phase": "during-settle",
      "controllerCurrentTime": 1.673,
      "controllerPendingSeek": 15,
      "controllerIsSeeking": true,
      "controllerSeekPreview": 15,
      "engineCurrentTime": 2.737,
      "engineDuration": 29.713,
      "storeCurrentTime": 1.673,
      "storeDuration": 29.713,
      "audioCurrentTime": null,
      "sliderValue": 1,
      "sliderMax": 29,
      "elapsedLabel": "0:01",
      "displayTimeFromSnapshot": 15
    },
    {
      "tMs": 8379,
      "phase": "during-settle",
      "controllerCurrentTime": 1.673,
      "controllerPendingSeek": 15,
      "controllerIsSeeking": true,
      "controllerSeekPreview": 15,
      "engineCurrentTime": 2.737,
      "engineDuration": 29.713,
      "storeCurrentTime": 1.673,
      "storeDuration": 29.713,
      "audioCurrentTime": null,
      "sliderValue": 1,
      "sliderMax": 29,
      "elapsedLabel": "0:01",
      "displayTimeFromSnapshot": 15
    },
    {
      "tMs": 8398,
      "phase": "during-settle",
      "controllerCurrentTime": 1.673,
      "controllerPendingSeek": 15,
      "controllerIsSeeking": true,
      "controllerSeekPreview": 15,
      "engineCurrentTime": 2.737,
      "engineDuration": 29.713,
      "storeCurrentTime": 1.673,
      "storeDuration": 29.713,
      "audioCurrentTime": null,
      "sliderValue": 1,
      "sliderMax": 29,
      "elapsedLabel": "0:01",
      "displayTimeFromSnapshot": 15
    },
    {
      "tMs": 8418,
      "phase": "during-settle",
      "controllerCurrentTime": 1.673,
      "controllerPendingSeek": 15,
      "controllerIsSeeking": true,
      "controllerSeekPreview": 15,
      "engineCurrentTime": 2.737,
      "engineDuration": 29.713,
      "storeCurrentTime": 1.673,
      "storeDuration": 29.713,
      "audioCurrentTime": null,
      "sliderValue": 1,
      "sliderMax": 29,
      "elapsedLabel": "0:01",
      "displayTimeFromSnapshot": 15
    },
    {
      "tMs": 8438,
      "phase": "during-settle",
      "controllerCurrentTime": 1.673,
      "controllerPendingSeek": 15,
      "controllerIsSeeking": true,
      "controllerSeekPreview": 15,
      "engineCurrentTime": 2.737,
      "engineDuration": 29.713,
      "storeCurrentTime": 1.673,
      "storeDuration": 29.713,
      "audioCurrentTime": null,
      "sliderValue": 1,
      "sliderMax": 29,
      "elapsedLabel": "0:01",
      "displayTimeFromSnapshot": 15
    },
    {
      "tMs": 8460,
      "phase": "during-settle",
      "controllerCurrentTime": 1.673,
      "controllerPendingSeek": 15,
      "controllerIsSeeking": true,
      "controllerSeekPreview": 15,
      "engineCurrentTime": 2.737,
      "engineDuration": 29.713,
      "storeCurrentTime": 1.673,
      "storeDuration": 29.713,
      "audioCurrentTime": null,
      "sliderValue": 1,
      "sliderMax": 29,
      "elapsedLabel": "0:01",
      "displayTimeFromSnapshot": 15
    },
    {
      "tMs": 8479,
      "phase": "during-settle",
      "controllerCurrentTime": 1.673,
      "controllerPendingSeek": 15,
      "controllerIsSeeking": true,
      "controllerSeekPreview": 15,
      "engineCurrentTime": 2.737,
      "engineDuration": 29.713,
      "storeCurrentTime": 1.673,
      "storeDuration": 29.713,
      "audioCurrentTime": null,
      "sliderValue": 1,
      "sliderMax": 29,
      "elapsedLabel": "0:01",
      "displayTimeFromSnapshot": 15
    },
    {
      "tMs": 8497,
      "phase": "during-settle",
      "controllerCurrentTime": 1.673,
      "controllerPendingSeek": 15,
      "controllerIsSeeking": true,
      "controllerSeekPreview": 15,
      "engineCurrentTime": 2.737,
      "engineDuration": 29.713,
      "storeCurrentTime": 1.673,
      "storeDuration": 29.713,
      "audioCurrentTime": null,
      "sliderValue": 1,
      "sliderMax": 29,
      "elapsedLabel": "0:01",
      "displayTimeFromSnapshot": 15
    },
    {
      "tMs": 8516,
      "phase": "during-settle",
      "controllerCurrentTime": 1.673,
      "controllerPendingSeek": 15,
      "controllerIsSeeking": true,
      "controllerSeekPreview": 15,
      "engineCurrentTime": 2.737,
      "engineDuration": 29.713,
      "storeCurrentTime": 1.673,
      "storeDuration": 29.713,
      "audioCurrentTime": null,
      "sliderValue": 1,
      "sliderMax": 29,
      "elapsedLabel": "0:01",
      "displayTimeFromSnapshot": 15
    },
    {
      "tMs": 8534,
      "phase": "during-settle",
      "controllerCurrentTime": 1.673,
      "controllerPendingSeek": 15,
      "controllerIsSeeking": true,
      "controllerSeekPreview": 15,
      "engineCurrentTime": 2.737,
      "engineDuration": 29.713,
      "storeCurrentTime": 1.673,
      "storeDuration": 29.713,
      "audioCurrentTime": null,
      "sliderValue": 1,
      "sliderMax": 29,
      "elapsedLabel": "0:01",
      "displayTimeFromSnapshot": 15
    },
    {
      "tMs": 8554,
      "phase": "during-settle",
      "controllerCurrentTime": 1.673,
      "controllerPendingSeek": 15,
      "controllerIsSeeking": true,
      "controllerSeekPreview": 15,
      "engineCurrentTime": 2.737,
      "engineDuration": 29.713,
      "storeCurrentTime": 1.673,
      "storeDuration": 29.713,
      "audioCurrentTime": null,
      "sliderValue": 1,
      "sliderMax": 29,
      "elapsedLabel": "0:01",
      "displayTimeFromSnapshot": 15
    },
    {
      "tMs": 8572,
      "phase": "during-settle",
      "controllerCurrentTime": 1.673,
      "controllerPendingSeek": 15,
      "controllerIsSeeking": true,
      "controllerSeekPreview": 15,
      "engineCurrentTime": 2.737,
      "engineDuration": 29.713,
      "storeCurrentTime": 1.673,
      "storeDuration": 29.713,
      "audioCurrentTime": null,
      "sliderValue": 1,
      "sliderMax": 29,
      "elapsedLabel": "0:01",
      "displayTimeFromSnapshot": 15
    },
    {
      "tMs": 8592,
      "phase": "during-settle",
      "controllerCurrentTime": 1.673,
      "controllerPendingSeek": 15,
      "controllerIsSeeking": true,
      "controllerSeekPreview": 15,
      "engineCurrentTime": 2.737,
      "engineDuration": 29.713,
      "storeCurrentTime": 1.673,
      "storeDuration": 29.713,
      "audioCurrentTime": null,
      "sliderValue": 1,
      "sliderMax": 29,
      "elapsedLabel": "0:01",
      "displayTimeFromSnapshot": 15
    },
    {
      "tMs": 8611,
      "phase": "during-settle",
      "controllerCurrentTime": 1.673,
      "controllerPendingSeek": 15,
      "controllerIsSeeking": true,
      "controllerSeekPreview": 15,
      "engineCurrentTime": 2.737,
      "engineDuration": 29.713,
      "storeCurrentTime": 1.673,
      "storeDuration": 29.713,
      "audioCurrentTime": null,
      "sliderValue": 1,
      "sliderMax": 29,
      "elapsedLabel": "0:01",
      "displayTimeFromSnapshot": 15
    },
    {
      "tMs": 8629,
      "phase": "during-settle",
      "controllerCurrentTime": 1.673,
      "controllerPendingSeek": 15,
      "controllerIsSeeking": true,
      "controllerSeekPreview": 15,
      "engineCurrentTime": 2.737,
      "engineDuration": 29.713,
      "storeCurrentTime": 1.673,
      "storeDuration": 29.713,
      "audioCurrentTime": null,
      "sliderValue": 1,
      "sliderMax": 29,
      "elapsedLabel": "0:01",
      "displayTimeFromSnapshot": 15
    },
    {
      "tMs": 8648,
      "phase": "during-settle",
      "controllerCurrentTime": 1.673,
      "controllerPendingSeek": 15,
      "controllerIsSeeking": true,
      "controllerSeekPreview": 15,
      "engineCurrentTime": 2.737,
      "engineDuration": 29.713,
      "storeCurrentTime": 1.673,
      "storeDuration": 29.713,
      "audioCurrentTime": null,
      "sliderValue": 1,
      "sliderMax": 29,
      "elapsedLabel": "0:01",
      "displayTimeFromSnapshot": 15
    },
    {
      "tMs": 8666,
      "phase": "during-settle",
      "controllerCurrentTime": 1.673,
      "controllerPendingSeek": 15,
      "controllerIsSeeking": true,
      "controllerSeekPreview": 15,
      "engineCurrentTime": 2.737,
      "engineDuration": 29.713,
      "storeCurrentTime": 1.673,
      "storeDuration": 29.713,
      "audioCurrentTime": null,
      "sliderValue": 1,
      "sliderMax": 29,
      "elapsedLabel": "0:01",
      "displayTimeFromSnapshot": 15
    },
    {
      "tMs": 8687,
      "phase": "during-settle",
      "controllerCurrentTime": 1.673,
      "controllerPendingSeek": 15,
      "controllerIsSeeking": true,
      "controllerSeekPreview": 15,
      "engineCurrentTime": 2.737,
      "engineDuration": 29.713,
      "storeCurrentTime": 1.673,
      "storeDuration": 29.713,
      "audioCurrentTime": null,
      "sliderValue": 1,
      "sliderMax": 29,
      "elapsedLabel": "0:01",
      "displayTimeFromSnapshot": 15
    },
    {
      "tMs": 8707,
      "phase": "during-settle",
      "controllerCurrentTime": 1.673,
      "controllerPendingSeek": 15,
      "controllerIsSeeking": true,
      "controllerSeekPreview": 15,
      "engineCurrentTime": 2.737,
      "engineDuration": 29.713,
      "storeCurrentTime": 1.673,
      "storeDuration": 29.713,
      "audioCurrentTime": null,
      "sliderValue": 1,
      "sliderMax": 29,
      "elapsedLabel": "0:01",
      "displayTimeFromSnapshot": 15
    },
    {
      "tMs": 8728,
      "phase": "during-settle",
      "controllerCurrentTime": 1.673,
      "controllerPendingSeek": 15,
      "controllerIsSeeking": true,
      "controllerSeekPreview": 15,
      "engineCurrentTime": 2.737,
      "engineDuration": 29.713,
      "storeCurrentTime": 1.673,
      "storeDuration": 29.713,
      "audioCurrentTime": null,
      "sliderValue": 1,
      "sliderMax": 29,
      "elapsedLabel": "0:01",
      "displayTimeFromSnapshot": 15
    },
    {
      "tMs": 8747,
      "phase": "during-settle",
      "controllerCurrentTime": 1.673,
      "controllerPendingSeek": 15,
      "controllerIsSeeking": true,
      "controllerSeekPreview": 15,
      "engineCurrentTime": 2.737,
      "engineDuration": 29.713,
      "storeCurrentTime": 1.673,
      "storeDuration": 29.713,
      "audioCurrentTime": null,
      "sliderValue": 1,
      "sliderMax": 29,
      "elapsedLabel": "0:01",
      "displayTimeFromSnapshot": 15
    },
    {
      "tMs": 8766,
      "phase": "during-settle",
      "controllerCurrentTime": 1.673,
      "controllerPendingSeek": 15,
      "controllerIsSeeking": true,
      "controllerSeekPreview": 15,
      "engineCurrentTime": 2.737,
      "engineDuration": 29.713,
      "storeCurrentTime": 1.673,
      "storeDuration": 29.713,
      "audioCurrentTime": null,
      "sliderValue": 1,
      "sliderMax": 29,
      "elapsedLabel": "0:01",
      "displayTimeFromSnapshot": 15
    },
    {
      "tMs": 8786,
      "phase": "during-settle",
      "controllerCurrentTime": 1.673,
      "controllerPendingSeek": 15,
      "controllerIsSeeking": true,
      "controllerSeekPreview": 15,
      "engineCurrentTime": 2.737,
      "engineDuration": 29.713,
      "storeCurrentTime": 1.673,
      "storeDuration": 29.713,
      "audioCurrentTime": null,
      "sliderValue": 1,
      "sliderMax": 29,
      "elapsedLabel": "0:01",
      "displayTimeFromSnapshot": 15
    },
    {
      "tMs": 8805,
      "phase": "during-settle",
      "controllerCurrentTime": 1.673,
      "controllerPendingSeek": 15,
      "controllerIsSeeking": true,
      "controllerSeekPreview": 15,
      "engineCurrentTime": 2.737,
      "engineDuration": 29.713,
      "storeCurrentTime": 1.673,
      "storeDuration": 29.713,
      "audioCurrentTime": null,
      "sliderValue": 1,
      "sliderMax": 29,
      "elapsedLabel": "0:01",
      "displayTimeFromSnapshot": 15
    },
    {
      "tMs": 8824,
      "phase": "during-settle",
      "controllerCurrentTime": 1.673,
      "controllerPendingSeek": 15,
      "controllerIsSeeking": true,
      "controllerSeekPreview": 15,
      "engineCurrentTime": 2.737,
      "engineDuration": 29.713,
      "storeCurrentTime": 1.673,
      "storeDuration": 29.713,
      "audioCurrentTime": null,
      "sliderValue": 1,
      "sliderMax": 29,
      "elapsedLabel": "0:01",
      "displayTimeFromSnapshot": 15
    },
    {
      "tMs": 8843,
      "phase": "during-settle",
      "controllerCurrentTime": 1.673,
      "controllerPendingSeek": 15,
      "controllerIsSeeking": true,
      "controllerSeekPreview": 15,
      "engineCurrentTime": 2.737,
      "engineDuration": 29.713,
      "storeCurrentTime": 1.673,
      "storeDuration": 29.713,
      "audioCurrentTime": null,
      "sliderValue": 1,
      "sliderMax": 29,
      "elapsedLabel": "0:01",
      "displayTimeFromSnapshot": 15
    },
    {
      "tMs": 8861,
      "phase": "during-settle",
      "controllerCurrentTime": 1.673,
      "controllerPendingSeek": 15,
      "controllerIsSeeking": true,
      "controllerSeekPreview": 15,
      "engineCurrentTime": 2.737,
      "engineDuration": 29.713,
      "storeCurrentTime": 1.673,
      "storeDuration": 29.713,
      "audioCurrentTime": null,
      "sliderValue": 1,
      "sliderMax": 29,
      "elapsedLabel": "0:01",
      "displayTimeFromSnapshot": 15
    },
    {
      "tMs": 8878,
      "phase": "during-settle",
      "controllerCurrentTime": 1.673,
      "controllerPendingSeek": 15,
      "controllerIsSeeking": true,
      "controllerSeekPreview": 15,
      "engineCurrentTime": 2.737,
      "engineDuration": 29.713,
      "storeCurrentTime": 1.673,
      "storeDuration": 29.713,
      "audioCurrentTime": null,
      "sliderValue": 1,
      "sliderMax": 29,
      "elapsedLabel": "0:01",
      "displayTimeFromSnapshot": 15
    },
    {
      "tMs": 8898,
      "phase": "during-settle",
      "controllerCurrentTime": 1.673,
      "controllerPendingSeek": 15,
      "controllerIsSeeking": true,
      "controllerSeekPreview": 15,
      "engineCurrentTime": 2.737,
      "engineDuration": 29.713,
      "storeCurrentTime": 1.673,
      "storeDuration": 29.713,
      "audioCurrentTime": null,
      "sliderValue": 1,
      "sliderMax": 29,
      "elapsedLabel": "0:01",
      "displayTimeFromSnapshot": 15
    },
    {
      "tMs": 8916,
      "phase": "during-settle",
      "controllerCurrentTime": 1.673,
      "controllerPendingSeek": 15,
      "controllerIsSeeking": true,
      "controllerSeekPreview": 15,
      "engineCurrentTime": 2.737,
      "engineDuration": 29.713,
      "storeCurrentTime": 1.673,
      "storeDuration": 29.713,
      "audioCurrentTime": null,
      "sliderValue": 1,
      "sliderMax": 29,
      "elapsedLabel": "0:01",
      "displayTimeFromSnapshot": 15
    },
    {
      "tMs": 8937,
      "phase": "during-settle",
      "controllerCurrentTime": 1.673,
      "controllerPendingSeek": 15,
      "controllerIsSeeking": true,
      "controllerSeekPreview": 15,
      "engineCurrentTime": 2.737,
      "engineDuration": 29.713,
      "storeCurrentTime": 1.673,
      "storeDuration": 29.713,
      "audioCurrentTime": null,
      "sliderValue": 1,
      "sliderMax": 29,
      "elapsedLabel": "0:01",
      "displayTimeFromSnapshot": 15
    },
    {
      "tMs": 8957,
      "phase": "during-settle",
      "controllerCurrentTime": 1.673,
      "controllerPendingSeek": 15,
      "controllerIsSeeking": true,
      "controllerSeekPreview": 15,
      "engineCurrentTime": 2.737,
      "engineDuration": 29.713,
      "storeCurrentTime": 1.673,
      "storeDuration": 29.713,
      "audioCurrentTime": null,
      "sliderValue": 1,
      "sliderMax": 29,
      "elapsedLabel": "0:01",
      "displayTimeFromSnapshot": 15
    },
    {
      "tMs": 8977,
      "phase": "during-settle",
      "controllerCurrentTime": 1.673,
      "controllerPendingSeek": 15,
      "controllerIsSeeking": true,
      "controllerSeekPreview": 15,
      "engineCurrentTime": 2.737,
      "engineDuration": 29.713,
      "storeCurrentTime": 1.673,
      "storeDuration": 29.713,
      "audioCurrentTime": null,
      "sliderValue": 1,
      "sliderMax": 29,
      "elapsedLabel": "0:01",
      "displayTimeFromSnapshot": 15
    },
    {
      "tMs": 8995,
      "phase": "during-settle",
      "controllerCurrentTime": 1.673,
      "controllerPendingSeek": 15,
      "controllerIsSeeking": true,
      "controllerSeekPreview": 15,
      "engineCurrentTime": 2.737,
      "engineDuration": 29.713,
      "storeCurrentTime": 1.673,
      "storeDuration": 29.713,
      "audioCurrentTime": null,
      "sliderValue": 1,
      "sliderMax": 29,
      "elapsedLabel": "0:01",
      "displayTimeFromSnapshot": 15
    },
    {
      "tMs": 9014,
      "phase": "during-settle",
      "controllerCurrentTime": 1.673,
      "controllerPendingSeek": 15,
      "controllerIsSeeking": true,
      "controllerSeekPreview": 15,
      "engineCurrentTime": 2.737,
      "engineDuration": 29.713,
      "storeCurrentTime": 1.673,
      "storeDuration": 29.713,
      "audioCurrentTime": null,
      "sliderValue": 1,
      "sliderMax": 29,
      "elapsedLabel": "0:01",
      "displayTimeFromSnapshot": 15
    },
    {
      "tMs": 9033,
      "phase": "during-settle",
      "controllerCurrentTime": 1.673,
      "controllerPendingSeek": 15,
      "controllerIsSeeking": true,
      "controllerSeekPreview": 15,
      "engineCurrentTime": 2.737,
      "engineDuration": 29.713,
      "storeCurrentTime": 1.673,
      "storeDuration": 29.713,
      "audioCurrentTime": null,
      "sliderValue": 1,
      "sliderMax": 29,
      "elapsedLabel": "0:01",
      "displayTimeFromSnapshot": 15
    },
    {
      "tMs": 9052,
      "phase": "during-settle",
      "controllerCurrentTime": 1.673,
      "controllerPendingSeek": 15,
      "controllerIsSeeking": true,
      "controllerSeekPreview": 15,
      "engineCurrentTime": 2.737,
      "engineDuration": 29.713,
      "storeCurrentTime": 1.673,
      "storeDuration": 29.713,
      "audioCurrentTime": null,
      "sliderValue": 1,
      "sliderMax": 29,
      "elapsedLabel": "0:01",
      "displayTimeFromSnapshot": 15
    },
    {
      "tMs": 9072,
      "phase": "during-settle",
      "controllerCurrentTime": 1.673,
      "controllerPendingSeek": 15,
      "controllerIsSeeking": true,
      "controllerSeekPreview": 15,
      "engineCurrentTime": 2.737,
      "engineDuration": 29.713,
      "storeCurrentTime": 1.673,
      "storeDuration": 29.713,
      "audioCurrentTime": null,
      "sliderValue": 1,
      "sliderMax": 29,
      "elapsedLabel": "0:01",
      "displayTimeFromSnapshot": 15
    },
    {
      "tMs": 9096,
      "phase": "during-settle",
      "controllerCurrentTime": 1.673,
      "controllerPendingSeek": 15,
      "controllerIsSeeking": true,
      "controllerSeekPreview": 15,
      "engineCurrentTime": 3.802,
      "engineDuration": 29.713,
      "storeCurrentTime": 1.673,
      "storeDuration": 29.713,
      "audioCurrentTime": null,
      "sliderValue": 1,
      "sliderMax": 29,
      "elapsedLabel": "0:01",
      "displayTimeFromSnapshot": 15
    },
    {
      "tMs": 9114,
      "phase": "during-settle",
      "controllerCurrentTime": 1.673,
      "controllerPendingSeek": 15,
      "controllerIsSeeking": true,
      "controllerSeekPreview": 15,
      "engineCurrentTime": 3.802,
      "engineDuration": 29.713,
      "storeCurrentTime": 1.673,
      "storeDuration": 29.713,
      "audioCurrentTime": null,
      "sliderValue": 1,
      "sliderMax": 29,
      "elapsedLabel": "0:01",
      "displayTimeFromSnapshot": 15
    },
    {
      "tMs": 9133,
      "phase": "during-settle",
      "controllerCurrentTime": 1.673,
      "controllerPendingSeek": 15,
      "controllerIsSeeking": true,
      "controllerSeekPreview": 15,
      "engineCurrentTime": 3.802,
      "engineDuration": 29.713,
      "storeCurrentTime": 1.673,
      "storeDuration": 29.713,
      "audioCurrentTime": null,
      "sliderValue": 1,
      "sliderMax": 29,
      "elapsedLabel": "0:01",
      "displayTimeFromSnapshot": 15
    },
    {
      "tMs": 9152,
      "phase": "during-settle",
      "controllerCurrentTime": 1.673,
      "controllerPendingSeek": 15,
      "controllerIsSeeking": true,
      "controllerSeekPreview": 15,
      "engineCurrentTime": 3.802,
      "engineDuration": 29.713,
      "storeCurrentTime": 1.673,
      "storeDuration": 29.713,
      "audioCurrentTime": null,
      "sliderValue": 1,
      "sliderMax": 29,
      "elapsedLabel": "0:01",
      "displayTimeFromSnapshot": 15
    },
    {
      "tMs": 9171,
      "phase": "during-settle",
      "controllerCurrentTime": 1.673,
      "controllerPendingSeek": 15,
      "controllerIsSeeking": true,
      "controllerSeekPreview": 15,
      "engineCurrentTime": 3.802,
      "engineDuration": 29.713,
      "storeCurrentTime": 1.673,
      "storeDuration": 29.713,
      "audioCurrentTime": null,
      "sliderValue": 1,
      "sliderMax": 29,
      "elapsedLabel": "0:01",
      "displayTimeFromSnapshot": 15
    },
    {
      "tMs": 9189,
      "phase": "post-settle-2s",
      "controllerCurrentTime": 1.673,
      "controllerPendingSeek": 15,
      "controllerIsSeeking": true,
      "controllerSeekPreview": 15,
      "engineCurrentTime": 3.802,
      "engineDuration": 29.713,
      "storeCurrentTime": 1.673,
      "storeDuration": 29.713,
      "audioCurrentTime": null,
      "sliderValue": 1,
      "sliderMax": 29,
      "elapsedLabel": "0:01",
      "displayTimeFromSnapshot": 15
    }
  ],
  "anomalies": [
    {
      "tMs": 7170,
      "field": "sliderValue",
      "value": 1,
      "expected": 14,
      "reason": "seek slider snap-back"
    },
    {
      "tMs": 7170,
      "field": "engineCurrentTime",
      "value": 1.673,
      "expected": 14,
      "reason": "engine never reached seek target"
    },
    {
      "tMs": 7171,
      "field": "sliderValue",
      "value": 1,
      "expected": 14,
      "reason": "seek slider snap-back"
    },
    {
      "tMs": 7171,
      "field": "engineCurrentTime",
      "value": 1.673,
      "expected": 14,
      "reason": "engine never reached seek target"
    },
    {
      "tMs": 7190,
      "field": "sliderValue",
      "value": 1,
      "expected": 14,
      "reason": "seek slider snap-back"
    },
    {
      "tMs": 7190,
      "field": "engineCurrentTime",
      "value": 1.673,
      "expected": 14,
      "reason": "engine never reached seek target"
    },
    {
      "tMs": 7208,
      "field": "sliderValue",
      "value": 1,
      "expected": 14,
      "reason": "seek slider snap-back"
    },
    {
      "tMs": 7208,
      "field": "engineCurrentTime",
      "value": 1.673,
      "expected": 14,
      "reason": "engine never reached seek target"
    },
    {
      "tMs": 7226,
      "field": "sliderValue",
      "value": 1,
      "expected": 14,
      "reason": "seek slider snap-back"
    },
    {
      "tMs": 7226,
      "field": "engineCurrentTime",
      "value": 1.673,
      "expected": 14,
      "reason": "engine never reached seek target"
    },
    {
      "tMs": 7245,
      "field": "sliderValue",
      "value": 1,
      "expected": 14,
      "reason": "seek slider snap-back"
    },
    {
      "tMs": 7245,
      "field": "engineCurrentTime",
      "value": 1.673,
      "expected": 14,
      "reason": "engine never reached seek target"
    },
    {
      "tMs": 7263,
      "field": "sliderValue",
      "value": 1,
      "expected": 14,
      "reason": "seek slider snap-back"
    },
    {
      "tMs": 7263,
      "field": "engineCurrentTime",
      "value": 1.673,
      "expected": 14,
      "reason": "engine never reached seek target"
    },
    {
      "tMs": 7282,
      "field": "sliderValue",
      "value": 1,
      "expected": 14,
      "reason": "seek slider snap-back"
    },
    {
      "tMs": 7282,
      "field": "engineCurrentTime",
      "value": 1.673,
      "expected": 14,
      "reason": "engine never reached seek target"
    },
    {
      "tMs": 7300,
      "field": "sliderValue",
      "value": 1,
      "expected": 14,
      "reason": "seek slider snap-back"
    },
    {
      "tMs": 7300,
      "field": "engineCurrentTime",
      "value": 1.673,
      "expected": 14,
      "reason": "engine never reached seek target"
    },
    {
      "tMs": 7318,
      "field": "sliderValue",
      "value": 1,
      "expected": 14,
      "reason": "seek slider snap-back"
    },
    {
      "tMs": 7318,
      "field": "engineCurrentTime",
      "value": 1.673,
      "expected": 14,
      "reason": "engine never reached seek target"
    },
    {
      "tMs": 7336,
      "field": "sliderValue",
      "value": 1,
      "expected": 14,
      "reason": "seek slider snap-back"
    },
    {
      "tMs": 7336,
      "field": "engineCurrentTime",
      "value": 1.673,
      "expected": 14,
      "reason": "engine never reached seek target"
    },
    {
      "tMs": 7354,
      "field": "sliderValue",
      "value": 1,
      "expected": 14,
      "reason": "seek slider snap-back"
    },
    {
      "tMs": 7354,
      "field": "engineCurrentTime",
      "value": 1.673,
      "expected": 14,
      "reason": "engine never reached seek target"
    },
    {
      "tMs": 7372,
      "field": "sliderValue",
      "value": 1,
      "expected": 14,
      "reason": "seek slider snap-back"
    },
    {
      "tMs": 7372,
      "field": "engineCurrentTime",
      "value": 1.673,
      "expected": 14,
      "reason": "engine never reached seek target"
    },
    {
      "tMs": 7391,
      "field": "sliderValue",
      "value": 1,
      "expected": 14,
      "reason": "seek slider snap-back"
    },
    {
      "tMs": 7391,
      "field": "engineCurrentTime",
      "value": 1.673,
      "expected": 14,
      "reason": "engine never reached seek target"
    },
    {
      "tMs": 7409,
      "field": "sliderValue",
      "value": 1,
      "expected": 14,
      "reason": "seek slider snap-back"
    },
    {
      "tMs": 7409,
      "field": "engineCurrentTime",
      "value": 1.673,
      "expected": 14,
      "reason": "engine never reached seek target"
    },
    {
      "tMs": 7426,
      "field": "sliderValue",
      "value": 1,
      "expected": 14,
      "reason": "seek slider snap-back"
    },
    {
      "tMs": 7426,
      "field": "engineCurrentTime",
      "value": 1.673,
      "expected": 14,
      "reason": "engine never reached seek target"
    },
    {
      "tMs": 7444,
      "field": "sliderValue",
      "value": 1,
      "expected": 14,
      "reason": "seek slider snap-back"
    },
    {
      "tMs": 7444,
      "field": "engineCurrentTime",
      "value": 1.673,
      "expected": 14,
      "reason": "engine never reached seek target"
    },
    {
      "tMs": 7462,
      "field": "sliderValue",
      "value": 1,
      "expected": 14,
      "reason": "seek slider snap-back"
    },
    {
      "tMs": 7462,
      "field": "engineCurrentTime",
      "value": 1.673,
      "expected": 14,
      "reason": "engine never reached seek target"
    },
    {
      "tMs": 7480,
      "field": "sliderValue",
      "value": 1,
      "expected": 14,
      "reason": "seek slider snap-back"
    },
    {
      "tMs": 7480,
      "field": "engineCurrentTime",
      "value": 1.673,
      "expected": 14,
      "reason": "engine never reached seek target"
    },
    {
      "tMs": 7498,
      "field": "sliderValue",
      "value": 1,
      "expected": 14,
      "reason": "seek slider snap-back"
    },
    {
      "tMs": 7498,
      "field": "engineCurrentTime",
      "value": 1.673,
      "expected": 14,
      "reason": "engine never reached seek target"
    },
    {
      "tMs": 7517,
      "field": "sliderValue",
      "value": 1,
      "expected": 14,
      "reason": "seek slider snap-back"
    },
    {
      "tMs": 7517,
      "field": "engineCurrentTime",
      "value": 1.673,
      "expected": 14,
      "reason": "engine never reached seek target"
    },
    {
      "tMs": 7535,
      "field": "sliderValue",
      "value": 1,
      "expected": 14,
      "reason": "seek slider snap-back"
    },
    {
      "tMs": 7535,
      "field": "engineCurrentTime",
      "value": 1.673,
      "expected": 14,
      "reason": "engine never reached seek target"
    },
    {
      "tMs": 7554,
      "field": "sliderValue",
      "value": 1,
      "expected": 14,
      "reason": "seek slider snap-back"
    },
    {
      "tMs": 7554,
      "field": "engineCurrentTime",
      "value": 1.673,
      "expected": 14,
      "reason": "engine never reached seek target"
    },
    {
      "tMs": 7573,
      "field": "sliderValue",
      "value": 1,
      "expected": 14,
      "reason": "seek slider snap-back"
    },
    {
      "tMs": 7573,
      "field": "engineCurrentTime",
      "value": 1.673,
      "expected": 14,
      "reason": "engine never reached seek target"
    },
    {
      "tMs": 7592,
      "field": "sliderValue",
      "value": 1,
      "expected": 14,
      "reason": "seek slider snap-back"
    },
    {
      "tMs": 7592,
      "field": "engineCurrentTime",
      "value": 1.673,
      "expected": 14,
      "reason": "engine never reached seek target"
    },
    {
      "tMs": 7612,
      "field": "sliderValue",
      "value": 1,
      "expected": 14,
      "reason": "seek slider snap-back"
    },
    {
      "tMs": 7612,
      "field": "engineCurrentTime",
      "value": 1.673,
      "expected": 14,
      "reason": "engine never reached seek target"
    },
    {
      "tMs": 7630,
      "field": "sliderValue",
      "value": 1,
      "expected": 14,
      "reason": "seek slider snap-back"
    },
    {
      "tMs": 7630,
      "field": "engineCurrentTime",
      "value": 1.673,
      "expected": 14,
      "reason": "engine never reached seek target"
    },
    {
      "tMs": 7650,
      "field": "sliderValue",
      "value": 1,
      "expected": 14,
      "reason": "seek slider snap-back"
    },
    {
      "tMs": 7650,
      "field": "engineCurrentTime",
      "value": 1.673,
      "expected": 14,
      "reason": "engine never reached seek target"
    },
    {
      "tMs": 7669,
      "field": "sliderValue",
      "value": 1,
      "expected": 14,
      "reason": "seek slider snap-back"
    },
    {
      "tMs": 7669,
      "field": "engineCurrentTime",
      "value": 1.673,
      "expected": 14,
      "reason": "engine never reached seek target"
    },
    {
      "tMs": 7688,
      "field": "engineCurrentTime",
      "value": 1.673,
      "expected": 14,
      "reason": "engine never reached seek target"
    },
    {
      "tMs": 7709,
      "field": "engineCurrentTime",
      "value": 1.673,
      "expected": 14,
      "reason": "engine never reached seek target"
    },
    {
      "tMs": 7729,
      "field": "engineCurrentTime",
      "value": 1.673,
      "expected": 14,
      "reason": "engine never reached seek target"
    },
    {
      "tMs": 7748,
      "field": "engineCurrentTime",
      "value": 1.673,
      "expected": 14,
      "reason": "engine never reached seek target"
    },
    {
      "tMs": 7765,
      "field": "engineCurrentTime",
      "value": 1.673,
      "expected": 14,
      "reason": "engine never reached seek target"
    },
    {
      "tMs": 7784,
      "field": "engineCurrentTime",
      "value": 1.673,
      "expected": 14,
      "reason": "engine never reached seek target"
    },
    {
      "tMs": 7802,
      "field": "engineCurrentTime",
      "value": 1.673,
      "expected": 14,
      "reason": "engine never reached seek target"
    },
    {
      "tMs": 7821,
      "field": "engineCurrentTime",
      "value": 1.673,
      "expected": 14,
      "reason": "engine never reached seek target"
    },
    {
      "tMs": 7841,
      "field": "engineCurrentTime",
      "value": 1.673,
      "expected": 14,
      "reason": "engine never reached seek target"
    },
    {
      "tMs": 7860,
      "field": "engineCurrentTime",
      "value": 1.673,
      "expected": 14,
      "reason": "engine never reached seek target"
    },
    {
      "tMs": 7879,
      "field": "engineCurrentTime",
      "value": 1.673,
      "expected": 14,
      "reason": "engine never reached seek target"
    },
    {
      "tMs": 7897,
      "field": "engineCurrentTime",
      "value": 1.673,
      "expected": 14,
      "reason": "engine never reached seek target"
    },
    {
      "tMs": 7915,
      "field": "engineCurrentTime",
      "value": 1.673,
      "expected": 14,
      "reason": "engine never reached seek target"
    },
    {
      "tMs": 7934,
      "field": "engineCurrentTime",
      "value": 1.673,
      "expected": 14,
      "reason": "engine never reached seek target"
    },
    {
      "tMs": 7953,
      "field": "engineCurrentTime",
      "value": 1.673,
      "expected": 14,
      "reason": "engine never reached seek target"
    },
    {
      "tMs": 7974,
      "field": "engineCurrentTime",
      "value": 1.673,
      "expected": 14,
      "reason": "engine never reached seek target"
    },
    {
      "tMs": 7994,
      "field": "engineCurrentTime",
      "value": 1.673,
      "expected": 14,
      "reason": "engine never reached seek target"
    },
    {
      "tMs": 8012,
      "field": "engineCurrentTime",
      "value": 1.673,
      "expected": 14,
      "reason": "engine never reached seek target"
    },
    {
      "tMs": 8031,
      "field": "engineCurrentTime",
      "value": 2.737,
      "expected": 14,
      "reason": "engine never reached seek target"
    },
    {
      "tMs": 8049,
      "field": "engineCurrentTime",
      "value": 2.737,
      "expected": 14,
      "reason": "engine never reached seek target"
    },
    {
      "tMs": 8067,
      "field": "engineCurrentTime",
      "value": 2.737,
      "expected": 14,
      "reason": "engine never reached seek target"
    },
    {
      "tMs": 8085,
      "field": "engineCurrentTime",
      "value": 2.737,
      "expected": 14,
      "reason": "engine never reached seek target"
    },
    {
      "tMs": 8104,
      "field": "engineCurrentTime",
      "value": 2.737,
      "expected": 14,
      "reason": "engine never reached seek target"
    },
    {
      "tMs": 8122,
      "field": "engineCurrentTime",
      "value": 2.737,
      "expected": 14,
      "reason": "engine never reached seek target"
    },
    {
      "tMs": 8140,
      "field": "engineCurrentTime",
      "value": 2.737,
      "expected": 14,
      "reason": "engine never reached seek target"
    },
    {
      "tMs": 8158,
      "field": "engineCurrentTime",
      "value": 2.737,
      "expected": 14,
      "reason": "engine never reached seek target"
    },
    {
      "tMs": 8176,
      "field": "engineCurrentTime",
      "value": 2.737,
      "expected": 14,
      "reason": "engine never reached seek target"
    },
    {
      "tMs": 8194,
      "field": "engineCurrentTime",
      "value": 2.737,
      "expected": 14,
      "reason": "engine never reached seek target"
    },
    {
      "tMs": 8212,
      "field": "engineCurrentTime",
      "value": 2.737,
      "expected": 14,
      "reason": "engine never reached seek target"
    },
    {
      "tMs": 8230,
      "field": "engineCurrentTime",
      "value": 2.737,
      "expected": 14,
      "reason": "engine never reached seek target"
    },
    {
      "tMs": 8249,
      "field": "engineCurrentTime",
      "value": 2.737,
      "expected": 14,
      "reason": "engine never reached seek target"
    },
    {
      "tMs": 8267,
      "field": "engineCurrentTime",
      "value": 2.737,
      "expected": 14,
      "reason": "engine never reached seek target"
    },
    {
      "tMs": 8286,
      "field": "engineCurrentTime",
      "value": 2.737,
      "expected": 14,
      "reason": "engine never reached seek target"
    },
    {
      "tMs": 8304,
      "field": "engineCurrentTime",
      "value": 2.737,
      "expected": 14,
      "reason": "engine never reached seek target"
    },
    {
      "tMs": 8323,
      "field": "engineCurrentTime",
      "value": 2.737,
      "expected": 14,
      "reason": "engine never reached seek target"
    },
    {
      "tMs": 8342,
      "field": "engineCurrentTime",
      "value": 2.737,
      "expected": 14,
      "reason": "engine never reached seek target"
    },
    {
      "tMs": 8361,
      "field": "engineCurrentTime",
      "value": 2.737,
      "expected": 14,
      "reason": "engine never reached seek target"
    },
    {
      "tMs": 8379,
      "field": "engineCurrentTime",
      "value": 2.737,
      "expected": 14,
      "reason": "engine never reached seek target"
    },
    {
      "tMs": 8398,
      "field": "engineCurrentTime",
      "value": 2.737,
      "expected": 14,
      "reason": "engine never reached seek target"
    },
    {
      "tMs": 8418,
      "field": "engineCurrentTime",
      "value": 2.737,
      "expected": 14,
      "reason": "engine never reached seek target"
    },
    {
      "tMs": 8438,
      "field": "engineCurrentTime",
      "value": 2.737,
      "expected": 14,
      "reason": "engine never reached seek target"
    },
    {
      "tMs": 8460,
      "field": "engineCurrentTime",
      "value": 2.737,
      "expected": 14,
      "reason": "engine never reached seek target"
    },
    {
      "tMs": 8479,
      "field": "engineCurrentTime",
      "value": 2.737,
      "expected": 14,
      "reason": "engine never reached seek target"
    },
    {
      "tMs": 8497,
      "field": "engineCurrentTime",
      "value": 2.737,
      "expected": 14,
      "reason": "engine never reached seek target"
    },
    {
      "tMs": 8516,
      "field": "engineCurrentTime",
      "value": 2.737,
      "expected": 14,
      "reason": "engine never reached seek target"
    },
    {
      "tMs": 8534,
      "field": "engineCurrentTime",
      "value": 2.737,
      "expected": 14,
      "reason": "engine never reached seek target"
    },
    {
      "tMs": 8554,
      "field": "engineCurrentTime",
      "value": 2.737,
      "expected": 14,
      "reason": "engine never reached seek target"
    },
    {
      "tMs": 8572,
      "field": "engineCurrentTime",
      "value": 2.737,
      "expected": 14,
      "reason": "engine never reached seek target"
    },
    {
      "tMs": 8592,
      "field": "engineCurrentTime",
      "value": 2.737,
      "expected": 14,
      "reason": "engine never reached seek target"
    },
    {
      "tMs": 8611,
      "field": "engineCurrentTime",
      "value": 2.737,
      "expected": 14,
      "reason": "engine never reached seek target"
    },
    {
      "tMs": 8629,
      "field": "engineCurrentTime",
      "value": 2.737,
      "expected": 14,
      "reason": "engine never reached seek target"
    },
    {
      "tMs": 8648,
      "field": "engineCurrentTime",
      "value": 2.737,
      "expected": 14,
      "reason": "engine never reached seek target"
    },
    {
      "tMs": 8666,
      "field": "engineCurrentTime",
      "value": 2.737,
      "expected": 14,
      "reason": "engine never reached seek target"
    },
    {
      "tMs": 8687,
      "field": "engineCurrentTime",
      "value": 2.737,
      "expected": 14,
      "reason": "engine never reached seek target"
    },
    {
      "tMs": 8707,
      "field": "engineCurrentTime",
      "value": 2.737,
      "expected": 14,
      "reason": "engine never reached seek target"
    },
    {
      "tMs": 8728,
      "field": "engineCurrentTime",
      "value": 2.737,
      "expected": 14,
      "reason": "engine never reached seek target"
    },
    {
      "tMs": 8747,
      "field": "engineCurrentTime",
      "value": 2.737,
      "expected": 14,
      "reason": "engine never reached seek target"
    },
    {
      "tMs": 8766,
      "field": "engineCurrentTime",
      "value": 2.737,
      "expected": 14,
      "reason": "engine never reached seek target"
    },
    {
      "tMs": 8786,
      "field": "engineCurrentTime",
      "value": 2.737,
      "expected": 14,
      "reason": "engine never reached seek target"
    },
    {
      "tMs": 8805,
      "field": "engineCurrentTime",
      "value": 2.737,
      "expected": 14,
      "reason": "engine never reached seek target"
    },
    {
      "tMs": 8824,
      "field": "engineCurrentTime",
      "value": 2.737,
      "expected": 14,
      "reason": "engine never reached seek target"
    },
    {
      "tMs": 8843,
      "field": "engineCurrentTime",
      "value": 2.737,
      "expected": 14,
      "reason": "engine never reached seek target"
    },
    {
      "tMs": 8861,
      "field": "engineCurrentTime",
      "value": 2.737,
      "expected": 14,
      "reason": "engine never reached seek target"
    },
    {
      "tMs": 8878,
      "field": "engineCurrentTime",
      "value": 2.737,
      "expected": 14,
      "reason": "engine never reached seek target"
    },
    {
      "tMs": 8898,
      "field": "engineCurrentTime",
      "value": 2.737,
      "expected": 14,
      "reason": "engine never reached seek target"
    },
    {
      "tMs": 8916,
      "field": "engineCurrentTime",
      "value": 2.737,
      "expected": 14,
      "reason": "engine never reached seek target"
    },
    {
      "tMs": 8937,
      "field": "engineCurrentTime",
      "value": 2.737,
      "expected": 14,
      "reason": "engine never reached seek target"
    },
    {
      "tMs": 8957,
      "field": "engineCurrentTime",
      "value": 2.737,
      "expected": 14,
      "reason": "engine never reached seek target"
    },
    {
      "tMs": 8977,
      "field": "engineCurrentTime",
      "value": 2.737,
      "expected": 14,
      "reason": "engine never reached seek target"
    },
    {
      "tMs": 8995,
      "field": "engineCurrentTime",
      "value": 2.737,
      "expected": 14,
      "reason": "engine never reached seek target"
    },
    {
      "tMs": 9014,
      "field": "engineCurrentTime",
      "value": 2.737,
      "expected": 14,
      "reason": "engine never reached seek target"
    },
    {
      "tMs": 9033,
      "field": "engineCurrentTime",
      "value": 2.737,
      "expected": 14,
      "reason": "engine never reached seek target"
    },
    {
      "tMs": 9052,
      "field": "engineCurrentTime",
      "value": 2.737,
      "expected": 14,
      "reason": "engine never reached seek target"
    },
    {
      "tMs": 9072,
      "field": "engineCurrentTime",
      "value": 2.737,
      "expected": 14,
      "reason": "engine never reached seek target"
    },
    {
      "tMs": 9096,
      "field": "engineCurrentTime",
      "value": 3.802,
      "expected": 14,
      "reason": "engine never reached seek target"
    },
    {
      "tMs": 9114,
      "field": "engineCurrentTime",
      "value": 3.802,
      "expected": 14,
      "reason": "engine never reached seek target"
    },
    {
      "tMs": 9133,
      "field": "engineCurrentTime",
      "value": 3.802,
      "expected": 14,
      "reason": "engine never reached seek target"
    },
    {
      "tMs": 9152,
      "field": "engineCurrentTime",
      "value": 3.802,
      "expected": 14,
      "reason": "engine never reached seek target"
    },
    {
      "tMs": 9171,
      "field": "engineCurrentTime",
      "value": 3.802,
      "expected": 14,
      "reason": "engine never reached seek target"
    },
    {
      "tMs": 9189,
      "field": "engineCurrentTime",
      "value": 3.802,
      "expected": 14,
      "reason": "engine never reached seek target"
    }
  ]
}