{
  "slug": "fernanda-martins",
  "tracks": [
    {
      "title": "Rampant",
      "spotifyTrackId": "1vHnk2PXmyPtPT2Dw8fmAy",
      "year": 2018,
      "duration": "6:09",
      "album": "Rampant"
    },
    {
      "title": "Trinity - Fernanda Martins Remix",
      "spotifyTrackId": "4bOfCFJkvAg3iXPi0cyOG3",
      "year": 2024,
      "duration": "5:38",
      "album": "Trinity (Fernanda Martins Remix)"
    },
    {
      "title": "Nothing Fancy - Fernanda Martins Remix",
      "spotifyTrackId": "526xkQdAzOiTmvIBHXMIMn",
      "year": 2018,
      "duration": "6:45",
      "album": "Nothing Fancy"
    },
    {
      "title": "Resonate - Lukas, Fernanda Martins Remix",
      "spotifyTrackId": "5F2ktpwjNSRC1u5AeyWqVH",
      "year": 2025,
      "duration": "6:42",
      "album": "Ego Disco"
    },
    {
      "title": "Scheme - Fernanda Martins Remix",
      "spotifyTrackId": "7FJdjrCCO2PJXLr5QsEOHh",
      "year": 2020,
      "duration": "6:09",
      "album": "N3URON"
    },
    {
      "title": "Definition of Hard Techno - Lukas & Fernanda Martins Remix",
      "spotifyTrackId": "3FhsfO5j8cD3a0xgHCAn9q",
      "year": 2015,
      "duration": "6:47",
      "album": "Definition of Hard Techno"
    }
  ],
  "sets": [],
  "updatedAt": "2026-07-18T02:41:23.247Z"
}
