{
  "slug": "norbak",
  "name": "Nørbak",
  "updatedAt": "2026-06-28T19:30:12.184Z",
  "sources": {
    "youtube": {
      "syncedAt": "2026-06-28T01:35:57.885Z",
      "status": "error",
      "error": "HTTP 429: {\n  \"error\": {\n    \"code\": 429,\n    \"message\": \"Quota exceeded for quota metric 'Search Queries' and limit 'Search Queries per day' of service 'youtube.googleapis.com' for consumer 'project_number:971"
    },
    "spotify": {
      "syncedAt": "2026-06-28T19:30:12.184Z",
      "status": "ok"
    }
  },
  "resolvedImage": {
    "url": "/images/portraits/researched/norbak.jpg",
    "source": "spotify",
    "sourceUrl": "https://open.spotify.com/artist/0TwXWZcwzGVVOa1Vdu3UEj"
  },
  "spotify": {
    "artistId": "0TwXWZcwzGVVOa1Vdu3UEj",
    "name": "Nørbak",
    "url": "https://open.spotify.com/artist/0TwXWZcwzGVVOa1Vdu3UEj",
    "genres": [],
    "followers": 0,
    "popularity": 0,
    "imageUrl": "/images/portraits/researched/norbak.jpg",
    "imageUrls": [
      "/images/portraits/researched/norbak.jpg"
    ],
    "relatedArtists": []
  }
}
